ocred/__init__.py
ocred/ocr.py
ocred/preprocessing.py
ocred/py.typed
ocred/version.py
ocred/version.pyi
ocred-0.4.0.dist-info/METADATA
ocred-0.4.0.dist-info/WHEEL
ocred-0.4.0.dist-info/licenses/LICENSE
ocred-0.4.0.dist-info/RECORD
