Metadata-Version: 2.1
Name: ocred
Version: 0.4.0
Summary: Clever, simple, and intuitive wrapper functionalities for OCRing specific textual materials
Project-URL: Bug Tracker, https://github.com/Saransh-cpp/OCRed/issues
Project-URL: Changelog, https://ocred.readthedocs.io/en/latest/changelog/
Project-URL: Discussions, https://github.com/Saransh-cpp/OCRed/discussions
Project-URL: Documentation, https://ocred.readthedocs.io/
Project-URL: Homepage, https://github.com/Saransh-cpp/OCRed
Author-email: Saransh Chopra <saransh0701@gmail.com>
License-Expression: MIT
License-File: LICENSE
Keywords: Computer Vision,Intended for direct users,OCR
Classifier: Development Status :: 5 - Production/Stable
Classifier: Intended Audience :: Customer Service
Classifier: Intended Audience :: Developers
Classifier: License :: OSI Approved :: MIT License
Classifier: Operating System :: OS Independent
Classifier: Programming Language :: Python
Classifier: Programming Language :: Python :: 3 :: Only
Classifier: Programming Language :: Python :: 3.7
Classifier: Programming Language :: Python :: 3.8
Classifier: Programming Language :: Python :: 3.9
Classifier: Programming Language :: Python :: 3.10
Classifier: Programming Language :: Python :: 3.11
Classifier: Topic :: Scientific/Engineering
Classifier: Typing :: Typed
Requires-Python: >=3.7
Requires-Dist: easyocr>=1.4.1
Requires-Dist: numpy>=1.19.3
Requires-Dist: opencv-python>=4.5.3.56
Requires-Dist: packaging
Requires-Dist: pillow<10.0.0
Requires-Dist: pytesseract>=0.3.8
Requires-Dist: scikit-image>=0.18.3
Requires-Dist: scipy>=1.5.4
Provides-Extra: dev
Requires-Dist: nltk>=3.5; extra == 'dev'
Requires-Dist: pytest-cov>=3; extra == 'dev'
Requires-Dist: pytest>=6; extra == 'dev'
Requires-Dist: xdoctest>=1; extra == 'dev'
Provides-Extra: docs
Requires-Dist: markdown-callouts>=0.2; extra == 'docs'
Requires-Dist: mkdocs-include-exclude-files>=0.0.1; extra == 'docs'
Requires-Dist: mkdocs-jupyter>=0.21; extra == 'docs'
Requires-Dist: mkdocs-material>=8.3.9; extra == 'docs'
Requires-Dist: mkdocs>=1.3.1; extra == 'docs'
Requires-Dist: mkdocstrings-python-legacy>=0.2.3; extra == 'docs'
Requires-Dist: mkdocstrings-python>=0.7.1; extra == 'docs'
Requires-Dist: pymdown-extensions>=9.5; extra == 'docs'
Provides-Extra: nltk
Requires-Dist: nltk>=3.5; extra == 'nltk'
Provides-Extra: test
Requires-Dist: pytest-cov>=3; extra == 'test'
Requires-Dist: pytest>=6; extra == 'test'
Requires-Dist: xdoctest>=1; extra == 'test'
